Metadata-Version: 1.0
Name: frankfnl-probability
Version: 0.1
Summary: Gaussian and Binomial distributions
Home-page: UNKNOWN
Author: Francisco Nava
Author-email: f.nava.morales92@gmail.com
License: UNKNOWN
Platform: UNKNOWN
